{
  "content": "{\"id\": \"4374d5d7-8730-402c-9c7b-43dc63e64bd0\", \"name\": \"Salvation Army Pontiac - Food Pantry\", \"alternate_name\": \"\", \"description\": \"\", \"email\": \"usc.socialmedia@usc.salvationarmy.org\", \"url\": \"\", \"status\": \"active\", \"address\": {\"address_1\": \"\", \"address_2\": \"\", \"city\": \"\", \"state_province\": \"\", \"postal_code\": \"\", \"country\": \"US\"}, \"phones\": [{\"number\": \"(248)3342407\", \"type\": \"voice\"}], \"location\": {\"latitude\": 42.6251492, \"longitude\": -83.2681087}, \"regular_schedule\": []}",
  "metadata": {
    "scraper_id": "getfull_app_api",
    "source": "getfull_app_api"
  },
  "timestamp": "2025-08-08T05:27:47.198284"
}