{
  "result": "{\n  \"organization\": {\n    \"name\": \"LITTLE JERUSALEM HOUSE OF PRAYER\",\n    \"alternate_name\": \"\",\n    \"description\": \"NYC Emergency Food Assistance Program (EFAP) location.\",\n    \"url\": null,\n    \"email\": null,\n    \"tax_id\": null,\n    \"dba\": null,\n    \"legal_name\": null,\n    \"parent_organization_id\": null,\n    \"metadata\": {\n      \"id\": \"org_1\",\n      \"last_action_date\": \"2023-10-27\"\n    }\n  },\n  \"locations\": [\n    {\n      \"name\": \"LITTLE JERUSALEM HOUSE OF PRAYER\",\n      \"alternate_name\": \"\",\n      \"description\": \"NYC Emergency Food Assistance Program (EFAP) location.\",\n      \"address\": {\n        \"address_1\": \"FP\",\n        \"address_2\": null,\n        \"city\": \"New York\",\n        \"state_province\": \"NY\",\n        \"postal_code\": \"11212\",\n        \"country\": \"US\",\n        \"address_type\": \"physical\"\n      },\n      \"coordinates\": {\n        \"latitude\": 40.658955,\n        \"longitude\": -73.912562\n      },\n      \"location_type\": \"physical\",\n      \"metadata\": {\n        \"id\": \"loc_1\",\n        \"last_action_date\": \"2023-10-27\"\n      }\n    }\n  ],\n  \"services\": [\n    {\n      \"name\": \"Emergency Food Assistance Program (EFAP)\",\n      \"alternate_name\": null,\n      \"description\": \"Provides emergency food assistance through the EFAP program.\",\n      \"organization_id\": \"org_1\",\n      \"location_ids\": [\n        \"loc_1\"\n      ],\n      \"status\": \"active\",\n      \"eligibility_requirements\": null,\n      \"fees\": null,\n      \"how_to_apply\": null,\n      \"schedule\": [\n        {\n          \"weekday\": \"MO\",\n          \"opens_at\": \"09:00\",\n          \"closes_at\": \"17:00\",\n          \"freq\": \"WEEKLY\",\n          \"wkst\": \"MO\",\n          \"repeat_rule\": null\n        }\n      ],\n      \"metadata\": {\n        \"id\": \"svc_1\",\n        \"last_action_date\": \"2023-10-27\"\n      }\n    }\n  ],\n  \"phones\": [\n    {\n      \"number\": \"7189227446\",\n      \"type\": \"voice\",\n      \"extension\": null,\n      \"language\": [\n        {\n          \"name\": \"English\"\n        }\n      ]\n    }\n  ],\n  \"addresses\": [],\n  \"emails\": [],\n  \"urls\": [],\n  \"schedules\": []\n}",
  "job_id": "1754629692.241752",
  "timestamp": "2025-08-08T05:22:21.453044"
}