{
  "content": "{\"name\": \"Springs SDA Community Services\", \"alternate_name\": \"\", \"description\": null, \"email\": \"\", \"url\": \"https://careandshare.org/locations/colorado-springs-central-sda-church/\", \"status\": \"active\", \"address\": {\"address_1\": \"1305 N Union Blvd\", \"address_2\": null, \"city\": \"Colorado Springs\", \"state_province\": \"CO\", \"postal_code\": \"80909\", \"country\": \"US\"}, \"location\": {\"latitude\": 38.8507, \"longitude\": -104.793816}, \"phones\": [{\"number\": \"(719) 634-1682\", \"type\": \"voice\"}]}",
  "metadata": {
    "scraper_id": "food_helpline_org",
    "source": "food_helpline_org"
  },
  "timestamp": "2025-08-08T05:08:56.139753"
}