{
  "result": "{\n  \"organization\": {\n    \"id\": \"org_39ebd0d9-ad8e-4901-8b90-4d94e7437a0a\",\n    \"name\": \"United Way-Bradford Area\",\n    \"alternate_name\": null,\n    \"description\": null,\n    \"email\": null,\n    \"url\": null,\n    \"status\": \"active\",\n    \"addresses\": [\n      {\n        \"address_type\": \"physical\",\n        \"address_1\": null,\n        \"address_2\": null,\n        \"city\": null,\n        \"state_province\": null,\n        \"postal_code\": null,\n        \"country\": \"US\",\n        \"coordinates\": {\n          \"latitude\": 41.9561754,\n          \"longitude\": -78.64495869999999\n        }\n      }\n    ],\n    \"phones\": [\n      {\n        \"number\": \"8143686181\",\n        \"type\": \"voice\",\n        \"languages\": [\n          {\n            \"name\": \"English\"\n          }\n        ]\n      }\n    ],\n    \"metadata\": {\n      \"last_action_date\": \"2023-10-27\"\n    }\n  },\n  \"services\": [\n    {\n      \"id\": \"svc_39ebd0d9-ad8e-4901-8b90-4d94e7437a0a\",\n      \"organization_id\": \"org_39ebd0d9-ad8e-4901-8b90-4d94e7437a0a\",\n      \"name\": null,\n      \"description\": null,\n      \"status\": \"active\",\n      \"metadata\": {\n        \"last_action_date\": \"2023-10-27\"\n      }\n    }\n  ],\n  \"locations\": [\n    {\n      \"id\": \"loc_39ebd0d9-ad8e-4901-8b90-4d94e7437a0a\",\n      \"organization_id\": \"org_39ebd0d9-ad8e-4901-8b90-4d94e7437a0a\",\n      \"service_id\": \"svc_39ebd0d9-ad8e-4901-8b90-4d94e7437a0a\",\n      \"name\": null,\n      \"location_type\": \"physical\",\n      \"addresses\": [\n        {\n          \"address_type\": \"physical\",\n          \"address_1\": null,\n          \"address_2\": null,\n          \"city\": null,\n          \"state_province\": null,\n          \"postal_code\": null,\n          \"country\": \"US\",\n          \"coordinates\": {\n            \"latitude\": 41.9561754,\n            \"longitude\": -78.64495869999999\n          }\n        }\n      ],\n      \"phones\": [\n        {\n          \"number\": \"8143686181\",\n          \"type\": \"voice\",\n          \"languages\": [\n            {\n              \"name\": \"English\"\n            }\n          ]\n        }\n      ],\n      \"metadata\": {\n        \"last_action_date\": \"2023-10-27\"\n      }\n    }\n  ]\n}",
  "job_id": "1754630845.145827",
  "timestamp": "2025-08-08T06:55:39.133300"
}