{
  "result": "```json\n{\n  \"id\": \"4942\",\n  \"name\": \"Westfield Mobile Food Bank\",\n  \"alternate_name\": \"\",\n  \"description\": \"Mobile food distribution program operated by the Food Bank of Western Massachusetts, providing food assistance with no eligibility requirements.\",\n  \"email\": \"\",\n  \"website\": \"\",\n  \"year_incorporated\": \"\",\n  \"legal_status\": \"\",\n  \"logo\": \"\",\n  \"uri\": \"\",\n  \"parent_organization_id\": \"\",\n  \"organization_identifiers\": [],\n  \"programs\": [],\n  \"contacts\": [],\n  \"locations\": [\n    {\n      \"id\": \"loc_4942\",\n      \"location_type\": \"physical\",\n      \"url\": \"\",\n      \"organization_id\": \"4942\",\n      \"name\": \"Westfield Mobile Food Bank Location\",\n      \"alternate_name\": \"\",\n      \"description\": \"Mobile food bank distribution site occurring the 1st & 3rd Monday of each month from 10:00-11:00 a.m.\",\n      \"transportation\": \"\",\n      \"latitude\": 42.117296,\n      \"longitude\": -72.747565,\n      \"external_identifier\": \"\",\n      \"external_identifier_type\": \"\",\n      \"phones\": [\n        {\n          \"number\": \"(413) 419-0079\",\n          \"type\": \"voice\",\n          \"languages\": [{\"name\": \"English\"}]\n        }\n      ],\n      \"accessibilitys\": [],\n      \"contacts\": [],\n      \"schedules\": [\n        {\n          \"freq\": \"MONTHLY\",\n          \"wkst\": \"MO\",\n          \"opens_at\": \"10:00\",\n          \"closes_at\": \"11:00\"\n        }\n      ],\n      \"languages\": [],\n      \"addresss\": [\n        {\n          \"id\": \"addr_4942\",\n          \"location_id\": \"loc_4942\",\n          \"attention\": \"\",\n          \"address_1\": \"60 Broad Street\",\n          \"address_2\": \"\",\n          \"city\": \"Westfield\",\n          \"region\": \"\",\n          \"state_province\": \"MA\",\n          \"postal_code\": \"01085\",\n          \"country\": \"US\",\n          \"address_type\": \"physical\",\n          \"attributes\": [],\n          \"metadata\": [\n            {\n              \"resource_id\": \"addr_4942\",\n              \"resource_type\": \"address\",\n              \"last_action_date\": \"2025-08-06\",\n              \"last_action_type\": \"create\"\n            }\n          ]\n        }\n      ],\n      \"attributes\": [],\n      \"metadata\": [\n        {\n          \"resource_id\": \"loc_4942\",\n          \"resource_type\": \"location\",\n          \"last_action_date\": \"2025-08-06\",\n          \"last_action_type\": \"create\"\n        }\n      ]\n    }\n  ],\n  \"fundings\": [],\n  \"phones\": [\n    {\n      \"number\": \"(413) 419-0079\",\n      \"type\": \"voice\",\n      \"languages\": [{\"name\": \"English\"}]\n    }\n  ],\n  \"attributes\": [],\n  \"metadata\": [\n    {\n      \"resource_id\": \"4942\",\n      \"resource_type\": \"organization\",\n      \"last_action_date\": \"2025-08-06\",\n      \"last_action_type\": \"create\"\n    }\n  ]\n}\n```",
  "job_id": "1754465973.185329",
  "timestamp": "2025-08-06T08:04:27.866313"
}