{
  "content": "{\"locationId\": \"7211\", \"organizationId\": \"6132\", \"name\": \"Williams Valley Food Pantry (SCA)\", \"address1\": \"536 E Grand Ave\", \"address2\": \"\", \"city\": \"Tower City\", \"state\": \"PA\", \"zipCode\": \"17980\", \"country\": null, \"phone\": \"\", \"phoneExt\": \"\", \"website\": \"\", \"latitude\": \"40.5892293\", \"longitude\": \"-76.5512842\", \"foodPrograms\": \"Food Distribution\", \"serviceAreas\": \"TOWNSHIP/NEIGHBORHOOD:  Williams Valley School District\", \"languages\": \"\", \"features\": \"\", \"aboutUs\": \"\", \"notes\": \"\", \"contactName\": \"\", \"contactPhone\": \"\", \"contactEmail\": \"\", \"servicePrograms\": \"\", \"foodServiceTypes\": \"Curbside Pickup / Drive Through, Outdoor Service\", \"dietRestrictions\": \"\", \"foodOfferings\": \"\", \"networkAffiliations\": [{\"regionId\": 53, \"regionName\": \"Helping Harvest Fresh Food Bank\", \"logoBlobNameSmall\": \"165e31c6-81ea-4cc6-b538-5a2e6d74bb62.png\", \"website\": \"https://helpingharvest.org/\"}], \"timeZoneName\": \"Eastern Standard Time\", \"timeZoneCode\": \"ET\", \"offsetHours\": \"-4\", \"schedules\": [\"Saturday 10:00 AM-11:30 AM\"], \"services\": [], \"specialHours\": []}",
  "metadata": {
    "scraper_id": "vivery_api",
    "source": "vivery_api"
  },
  "timestamp": "2025-08-04T08:26:45.774943"
}