{
  "result": "{\n  \"organizations\": [\n    {\n      \"id\": \"org_1\",\n      \"name\": \"Sunnyside Ministry of the Moravian Church\",\n      \"alternate_name\": null,\n      \"description\": \"Sunnyside Ministry is a food pantry.\",\n      \"email\": null,\n      \"url\": null,\n      \"status\": \"active\",\n      \"addresses\": [\n        {\n          \"address_type\": \"physical\",\n          \"address_1\": \"319 Haled Street\",\n          \"address_2\": null,\n          \"city\": \"Winston-Salem\",\n          \"state_province\": \"NC\",\n          \"postal_code\": \"27127\",\n          \"country\": \"US\",\n          \"coordinates\": {\n            \"latitude\": 36.0722005,\n            \"longitude\": -80.23278289999999\n          }\n        }\n      ],\n      \"phones\": [\n        {\n          \"number\": \"336-724-7558\",\n          \"type\": \"voice\",\n          \"languages\": [\n            {\n              \"name\": \"English\"\n            }\n          ]\n        }\n      ],\n      \"metadata\": {\n        \"last_action_date\": \"2023-10-27\"\n      }\n    }\n  ],\n  \"services\": [\n    {\n      \"id\": \"svc_1\",\n      \"organization_id\": \"org_1\",\n      \"name\": \"Food Pantry Services\",\n      \"description\": \"Provides food assistance, including diapers upon availability. Clients can visit once a month. Closed on major holidays.\",\n      \"status\": \"active\",\n      \"eligibility\": null,\n      \"fees\": null,\n      \"locations\": [\n        {\n          \"id\": \"loc_1\",\n          \"organization_id\": \"org_1\",\n          \"name\": \"Sunnyside Ministry Food Pantry\",\n          \"location_type\": \"physical\",\n          \"address_id\": \"address_1\",\n          \"metadata\": {\n            \"last_action_date\": \"2023-10-27\"\n          }\n        }\n      ],\n      \"schedule\": [\n        {\n          \"id\": \"sch_1\",\n          \"service_id\": \"svc_1\",\n          \"location_id\": \"loc_1\",\n          \"description\": \"Afternoon distribution\",\n          \"freq\": \"WEEKLY\",\n          \"wkst\": \"MO\",\n          \"days\": [\n            \"MONDAY\",\n            \"TUESDAY\",\n            \"WEDNESDAY\",\n            \"THURSDAY\",\n            \"FRIDAY\"\n          ],\n          \"opens_at\": \"14:00\",\n          \"closes_at\": \"16:00\",\n          \"metadata\": {\n            \"last_action_date\": \"2023-10-27\"\n          }\n        },\n        {\n          \"id\": \"sch_2\",\n          \"service_id\": \"svc_1\",\n          \"location_id\": \"loc_1\",\n          \"description\": \"Evening distribution\",\n          \"freq\": \"WEEKLY\",\n          \"wkst\": \"MO\",\n          \"days\": [\n            \"MONDAY\",\n            \"TUESDAY\",\n            \"WEDNESDAY\",\n            \"THURSDAY\"\n          ],\n          \"opens_at\": \"18:00\",\n          \"closes_at\": \"20:00\",\n          \"metadata\": {\n            \"last_action_date\": \"2023-10-27\"\n          }\n        }\n      ],\n      \"service_attributes\": [\n        {\n          \"attribute_key\": \"REQUIREMENT\",\n          \"attribute_value\": \"ID required\"\n        },\n        {\n          \"attribute_key\": \"OFFERING\",\n          \"attribute_value\": \"Clients can visit: Once a month\"\n        },\n        {\n          \"attribute_key\": \"OFFERING\",\n          \"attribute_value\": \"Diapers upon availability\"\n        },\n        {\n          \"attribute_key\": \"INFO\",\n          \"attribute_value\": \"Closed on major holidays\"\n        }\n      ],\n      \"metadata\": {\n        \"last_action_date\": \"2023-10-27\"\n      }\n    }\n  ]\n}",
  "job_id": "1754629755.901753",
  "timestamp": "2025-08-08T05:35:37.323041"
}