{
  "result": "{\n  \"id\": \"b7389f11-d61d-406e-aaeb-68d793f6a2d6\",\n  \"organization\": {\n    \"name\": \"Food Distribution Center - Knox County Food Cupboard\",\n    \"alternate_name\": \"\",\n    \"description\": \"A food pantry serving Knox County.\",\n    \"email\": null,\n    \"url\": null,\n    \"addresses\": [\n      {\n        \"address_type\": \"physical\",\n        \"address_1\": null,\n        \"address_2\": null,\n        \"city\": null,\n        \"state_province\": \"IA\",\n        \"postal_code\": null,\n        \"country\": \"US\"\n      }\n    ],\n    \"phones\": [],\n    \"metadata\": {\n      \"last_action_date\": \"2023-10-27\"\n    }\n  },\n  \"locations\": [\n    {\n      \"id\": \"loc_1\",\n      \"name\": \"Food Distribution Center - Knox County Food Cupboard\",\n      \"location_type\": \"physical\",\n      \"address\": {\n        \"address_type\": \"physical\",\n        \"address_1\": null,\n        \"address_2\": null,\n        \"city\": null,\n        \"state_province\": \"IA\",\n        \"postal_code\": null,\n        \"country\": \"US\"\n      },\n      \"coordinates\": {\n        \"latitude\": 40.1668313,\n        \"longitude\": -92.1742199\n      },\n      \"phones\": [],\n      \"metadata\": {\n        \"last_action_date\": \"2023-10-27\"\n      }\n    }\n  ],\n  \"services\": [\n    {\n      \"id\": \"svc_1\",\n      \"name\": \"Food Pantry Services\",\n      \"description\": \"Provides food assistance to individuals and families.\",\n      \"status\": \"active\",\n      \"locations\": [\n        {\n          \"location_id\": \"loc_1\",\n          \"provided_by\": [\n            \"b7389f11-d61d-406e-aaeb-68d793f6a2d6\"\n          ]\n        }\n      ],\n      \"schedule\": [],\n      \"metadata\": {\n        \"last_action_date\": \"2023-10-27\"\n      }\n    }\n  ]\n}",
  "job_id": "1754630825.803302",
  "timestamp": "2025-08-08T06:46:56.494906"
}