{
  "content": "{\"id\": \"855c4c6d-4458-46d8-88e2-ffe90c5ff810\", \"name\": \"Foundation Communities-Sierra Vista - Food Pantry\", \"alternate_name\": \"\", \"description\": \"\", \"email\": \"\", \"url\": \"\", \"status\": \"active\", \"address\": {\"address_1\": \"\", \"address_2\": \"\", \"city\": \"\", \"state_province\": \"\", \"postal_code\": \"\", \"country\": \"US\"}, \"phones\": [{\"number\": \"(512)8042265\", \"type\": \"voice\"}], \"location\": {\"latitude\": 30.219267, \"longitude\": -97.7672862}, \"regular_schedule\": []}",
  "metadata": {
    "scraper_id": "getfull_app_api",
    "source": "getfull_app_api"
  },
  "timestamp": "2025-08-08T05:25:28.776614"
}