{
  "content": "{\"name\": \"Gates Community Center\", \"alternate_name\": \"\", \"description\": null, \"email\": \"\", \"url\": null, \"status\": \"active\", \"address\": {\"address_1\": \"284 Southwest Cedar Street\", \"address_2\": null, \"city\": \"Mill City\", \"state_province\": \"OR\", \"postal_code\": \"97360\", \"country\": \"US\"}, \"location\": {\"latitude\": 44.7528254, \"longitude\": -122.4795196}, \"phones\": [{\"number\": \"(503) 897-4904\", \"type\": \"voice\"}], \"regular_schedule\": [{\"weekday\": \"Tuesday\", \"opens_at\": \"14:00\", \"closes_at\": \"16:00\"}, {\"weekday\": \"Thursday\", \"opens_at\": \"22:00\", \"closes_at\": \"00:00\"}]}",
  "metadata": {
    "scraper_id": "food_helpline_org",
    "source": "food_helpline_org"
  },
  "timestamp": "2025-08-06T08:40:28.441391"
}