{
  "content": "{\"name\": \"CALVARY TOUCH OF GOD CHURCH\", \"alternate_name\": \"\", \"description\": null, \"email\": \"\", \"url\": null, \"status\": \"active\", \"address\": {\"address_1\": \"636 Bergen Street\", \"address_2\": null, \"city\": \"Upper Clinton Hill\", \"state_province\": \"NJ\", \"postal_code\": \"07108\", \"country\": \"US\"}, \"location\": {\"latitude\": 40.7223126, \"longitude\": -74.1995558}, \"phones\": [{\"number\": \"(973) 848-1113\", \"type\": \"voice\"}], \"regular_schedule\": [{\"weekday\": \"Saturday\", \"opens_at\": \"\", \"closes_at\": \"\"}, {\"weekday\": \"Saturday\", \"opens_at\": \"\", \"closes_at\": \"\"}], \"service_attributes\": [{\"attribute_key\": \"REQUIREMENT\", \"attribute_value\": \"Appointments required\"}]}",
  "metadata": {
    "scraper_id": "food_helpline_org",
    "source": "food_helpline_org"
  },
  "timestamp": "2025-08-08T05:09:59.567931"
}