{
  "content": "{\"locationId\": \"14768\", \"organizationId\": \"11393\", \"name\": \"Feeding Chiefland\", \"address1\": \"707 N Main St\", \"address2\": null, \"city\": \"Chiefland\", \"state\": \"FL\", \"zipCode\": \"32626\", \"country\": null, \"phone\": \"352-493-4627\", \"phoneExt\": null, \"website\": null, \"latitude\": \"29.4850748\", \"longitude\": \"-82.8591837\", \"foodPrograms\": \"Food Distribution\", \"serviceAreas\": \"\", \"languages\": \"\", \"features\": \"\", \"aboutUs\": \"\", \"notes\": \"\", \"contactName\": null, \"contactPhone\": \"352-493-4627\", \"contactEmail\": \"Office@ChieflandMethodist.org\", \"servicePrograms\": \"\", \"foodServiceTypes\": \"\", \"dietRestrictions\": \"\", \"foodOfferings\": \"\", \"networkAffiliations\": [], \"timeZoneName\": \"Eastern Standard Time\", \"timeZoneCode\": \"ET\", \"offsetHours\": \"-4\", \"schedules\": [\"Friday 9:30 AM-11:30 AM (Walk Thru Event)\"], \"services\": [], \"specialHours\": []}",
  "metadata": {
    "scraper_id": "vivery_api",
    "source": "vivery_api"
  },
  "timestamp": "2025-08-06T08:46:33.383634"
}