{
  "result": "{\n  \"type\": \"Organization\",\n  \"hs_schema_version\": \"3.1.1\",\n  \"names\": [\n    {\n      \"value\": \"St. George's Episcopal Church - Food Pantry\",\n      \"lang\": \"en\"\n    }\n  ],\n  \"alternate_names\": [],\n  \"descriptions\": [\n    {\n      \"value\": \"St. George's Episcopal Church operates a food pantry offering assistance to those in need. Clothing may also be available. They are seeking volunteers and clients can visit once a week. The pantry is closed on major holidays.\",\n      \"lang\": \"en\"\n    }\n  ],\n  \"urls\": [\n    {\n      \"value\": \"http://stgeorgeschurchbedstuy.org/\",\n      \"type\": \"website\"\n    }\n  ],\n  \"email_addresses\": [],\n  \"addresses\": [\n    {\n      \"type\": \"physical\",\n      \"street_address_1\": \"800 Marcy Avenue\",\n      \"street_address_2\": null,\n      \"city\": \"Bedford-Stuyvesant\",\n      \"state_province\": \"NY\",\n      \"postal_code\": \"11216\",\n      \"country\": \"US\",\n      \"coordinates\": {\n        \"latitude\": 40.6863411,\n        \"longitude\": -73.9477843\n      }\n    }\n  ],\n  \"phones\": [\n    {\n      \"number\": \"7187896036\",\n      \"type\": \"voice\",\n      \"language\": [\n        {\n          \"name\": \"English\"\n        }\n      ]\n    }\n  ],\n  \"services\": [\n    {\n      \"type\": \"Food Pantry\",\n      \"hs_schema_version\": \"3.1.1\",\n      \"status\": \"active\",\n      \"descriptions\": [\n        {\n          \"value\": \"Food pantry services provided by St. George's Episcopal Church. Clients can visit once a week. Clothing may also be available.\",\n          \"lang\": \"en\"\n        }\n      ],\n      \"locations\": [\n        {\n          \"type\": \"physical\",\n          \"hs_schema_version\": \"3.1.1\",\n          \"addresses\": [\n            {\n              \"type\": \"physical\",\n              \"street_address_1\": \"800 Marcy Avenue\",\n              \"street_address_2\": null,\n              \"city\": \"Bedford-Stuyvesant\",\n              \"state_province\": \"NY\",\n              \"postal_code\": \"11216\",\n              \"country\": \"US\",\n              \"coordinates\": {\n                \"latitude\": 40.6863411,\n                \"longitude\": -73.9477843\n              }\n            }\n          ],\n          \"phones\": [],\n          \"regular_schedule\": [\n            {\n              \"weekday\": \"TU\",\n              \"opens_at\": \"16:00\",\n              \"closes_at\": \"18:00\",\n              \"freq\": \"WEEKLY\",\n              \"wkst\": \"MO\"\n            },\n            {\n              \"weekday\": \"WE\",\n              \"opens_at\": \"16:00\",\n              \"closes_at\": \"18:00\",\n              \"freq\": \"WEEKLY\",\n              \"wkst\": \"MO\"\n            },\n            {\n              \"weekday\": \"TH\",\n              \"opens_at\": \"16:00\",\n              \"closes_at\": \"18:00\",\n              \"freq\": \"WEEKLY\",\n              \"wkst\": \"MO\"\n            }\n          ],\n          \"metadata\": {\n            \"id\": \"loc_1\",\n            \"last_action_date\": \"2023-10-27\"\n          }\n        }\n      ],\n      \"service_attributes\": [\n        {\n          \"attribute_key\": \"INFO\",\n          \"attribute_value\": \"Needs volunteers\"\n        },\n        {\n          \"attribute_key\": \"INFO\",\n          \"attribute_value\": \"Client can visit: Once a week\"\n        },\n        {\n          \"attribute_key\": \"INFO\",\n          \"attribute_value\": \"Closed on major holidays\"\n        },\n        {\n          \"attribute_key\": \"OFFERING\",\n          \"attribute_value\": \"Clothing may be available\"\n        }\n      ],\n      \"metadata\": {\n        \"id\": \"svc_1\",\n        \"last_action_date\": \"2023-10-27\"\n      }\n    }\n  ],\n  \"metadata\": {\n    \"id\": \"org_1\",\n    \"last_action_date\": \"2023-10-27\"\n  }\n}",
  "job_id": "1754629805.543565",
  "timestamp": "2025-08-08T05:57:25.005051"
}