{
  "result": "{\n  \"organizations\": [\n    {\n      \"name\": \"Mission Hill Church - Six Miles Campus\",\n      \"alternate_name\": null,\n      \"description\": \"Mission Hill Church offers services at their Six Miles Campus.\",\n      \"url\": \"https://missionhill.org/\",\n      \"email\": null,\n      \"status\": \"active\",\n      \"addresses\": [\n        {\n          \"address_type\": \"physical\",\n          \"address_1\": \"4038 North Falkenburg Road\",\n          \"address_2\": null,\n          \"city\": \"Tampa\",\n          \"state_province\": \"FL\",\n          \"postal_code\": \"33610\",\n          \"country\": \"US\"\n        }\n      ],\n      \"phones\": [\n        {\n          \"number\": \"813-988-1138\",\n          \"type\": \"voice\",\n          \"languages\": [\n            {\n              \"name\": \"English\"\n            }\n          ]\n        }\n      ],\n      \"metadata\": {\n        \"org_id\": \"org_1\",\n        \"last_action_date\": \"2023-10-27\"\n      }\n    }\n  ],\n  \"services\": [\n    {\n      \"organization_id\": \"org_1\",\n      \"name\": \"Food Pantry Services\",\n      \"description\": \"Food pantry services are available on Thursdays, with clients able to visit once a week. Services are first come, first serve and open until food runs out. Clothing may also be available. Closed on major holidays. No specific requirements mentioned.\",\n      \"status\": \"active\",\n      \"locations\": [\n        {\n          \"location_id\": \"loc_1\",\n          \"location_type\": \"physical\",\n          \"addresses\": [\n            {\n              \"address_type\": \"physical\",\n              \"address_1\": \"4038 North Falkenburg Road\",\n              \"address_2\": null,\n              \"city\": \"Tampa\",\n              \"state_province\": \"FL\",\n              \"postal_code\": \"33610\",\n              \"country\": \"US\"\n            }\n          ],\n          \"coordinates\": {\n            \"latitude\": 27.9849305,\n            \"longitude\": -82.33541819999999\n          },\n          \"metadata\": {\n            \"loc_id\": \"loc_1\",\n            \"last_action_date\": \"2023-10-27\"\n          }\n        }\n      ],\n      \"schedule\": [\n        {\n          \"service_id\": \"svc_1\",\n          \"location_id\": \"loc_1\",\n          \"freq\": \"WEEKLY\",\n          \"wkst\": \"TH\",\n          \"time_open\": \"22:00\",\n          \"time_close\": \"00:00\"\n        },\n        {\n          \"service_id\": \"svc_1\",\n          \"location_id\": \"loc_1\",\n          \"freq\": \"WEEKLY\",\n          \"wkst\": \"TH\",\n          \"time_open\": \"23:00\",\n          \"time_close\": \"00:00\"\n        }\n      ],\n      \"service_attributes\": [\n        {\n          \"service_id\": \"svc_1\",\n          \"attribute_key\": \"INFO\",\n          \"attribute_value\": \"No requirements\"\n        },\n        {\n          \"service_id\": \"svc_1\",\n          \"attribute_key\": \"INFO\",\n          \"attribute_value\": \"Client can visit: Once a week\"\n        },\n        {\n          \"service_id\": \"svc_1\",\n          \"attribute_key\": \"INFO\",\n          \"attribute_value\": \"Closed on major holidays\"\n        },\n        {\n          \"service_id\": \"svc_1\",\n          \"attribute_key\": \"OFFERING\",\n          \"attribute_value\": \"Clothing may be available\"\n        },\n        {\n          \"service_id\": \"svc_1\",\n          \"attribute_key\": \"REQUIREMENT\",\n          \"attribute_value\": \"First come, first serve: open until food runs out\"\n        }\n      ],\n      \"metadata\": {\n        \"svc_id\": \"svc_1\",\n        \"last_action_date\": \"2023-10-27\"\n      }\n    }\n  ]\n}",
  "job_id": "1754629758.640528",
  "timestamp": "2025-08-08T05:36:51.775802"
}