{
  "result": "{\n  \"organization\": {\n    \"name\": \"Montrose Elementary\",\n    \"alternate_name\": null,\n    \"description\": \"Montrose Elementary offers an outdoor community fridge/pantry operated by local volunteers, open 24/7.\",\n    \"email\": null,\n    \"url\": null,\n    \"status\": \"active\",\n    \"addresses\": [\n      {\n        \"kind\": \"physical\",\n        \"address_1\": \"Remington Road Parking Lot\",\n        \"address_2\": \"2555 East Main Street\",\n        \"city\": \"Columbus\",\n        \"state_province\": \"OH\",\n        \"postal_code\": \"43209\",\n        \"country\": \"US\"\n      }\n    ],\n    \"phones\": [\n      {\n        \"kind\": \"voice\",\n        \"number\": \"(614) 237-4226\",\n        \"languages\": [\n          {\n            \"name\": \"English\"\n          }\n        ]\n      }\n    ],\n    \"metadata\": {\n      \"last_action_date\": \"2023-10-27\",\n      \"entity_id\": \"org_1\"\n    }\n  },\n  \"locations\": [\n    {\n      \"name\": \"Montrose Elementary\",\n      \"alternate_name\": null,\n      \"description\": \"Remington Road Parking Lot, 2555 East Main Street, Columbus, OH 43209\",\n      \"status\": \"active\",\n      \"addresses\": [\n        {\n          \"kind\": \"physical\",\n          \"address_1\": \"Remington Road Parking Lot\",\n          \"address_2\": \"2555 East Main Street\",\n          \"city\": \"Columbus\",\n          \"state_province\": \"OH\",\n          \"postal_code\": \"43209\",\n          \"country\": \"US\"\n        }\n      ],\n      \"coordinates\": {\n        \"latitude\": 39.9568337,\n        \"longitude\": -82.924478\n      },\n      \"phones\": [\n        {\n          \"kind\": \"voice\",\n          \"number\": \"(614) 237-4226\",\n          \"languages\": [\n            {\n              \"name\": \"English\"\n            }\n          ]\n        }\n      ],\n      \"schedule\": {\n        \"freq\": \"DAILY\",\n        \"wkst\": \"MO\",\n        \"time\": \"00:00\",\n        \"duration\": \"24h\"\n      },\n      \"metadata\": {\n        \"last_action_date\": \"2023-10-27\",\n        \"entity_id\": \"loc_1\"\n      }\n    }\n  ],\n  \"services\": [\n    {\n      \"name\": \"Community Fridge/Pantry\",\n      \"alternate_name\": null,\n      \"description\": \"This is a free, outdoor community fridge/pantry open 24/7, operated by local volunteers. Open to all.\",\n      \"status\": \"active\",\n      \"locations\": [\n        {\n          \"entity_id\": \"loc_1\"\n        }\n      ],\n      \"schedule\": {\n        \"freq\": \"DAILY\",\n        \"wkst\": \"MO\",\n        \"time\": \"00:00\",\n        \"duration\": \"24h\"\n      },\n      \"service_attributes\": [\n        {\n          \"attribute_key\": \"INFO\",\n          \"attribute_value\": \"Open to all\"\n        },\n        {\n          \"attribute_key\": \"INFO\",\n          \"attribute_value\": \"Open 24/7! Free, outdoor community fridge/pantry operated by local volunteers.\"\n        }\n      ],\n      \"metadata\": {\n        \"last_action_date\": \"2023-10-27\",\n        \"entity_id\": \"svc_1\"\n      }\n    }\n  ]\n}",
  "job_id": "1754629766.791048",
  "timestamp": "2025-08-08T05:40:03.990049"
}