{
  "result": "```json\n{\n  \"organization\": [\n    {\n      \"name\": \"Beltsville Adventist Community Center\",\n      \"email\": \"sifap@pcsda.org\",\n      \"description\": \"Community center providing food assistance services\",\n      \"services\": [\n        {\n          \"name\": \"Food Pantry\",\n          \"description\": \"Food distribution service\",\n          \"status\": \"active\",\n          \"phones\": [\n            {\n              \"number\": \"(301) 996-7803\",\n              \"type\": \"voice\",\n              \"languages\": [\n                {\n                  \"name\": \"English\"\n                }\n              ]\n            }\n          ],\n          \"schedules\": [\n            {\n              \"freq\": \"WEEKLY\",\n              \"wkst\": \"TU\",\n              \"opens_at\": \"09:00\",\n              \"closes_at\": \"14:00\"\n            },\n            {\n              \"freq\": \"WEEKLY\",\n              \"wkst\": \"WE\",\n              \"opens_at\": \"09:00\",\n              \"closes_at\": \"14:00\"\n            },\n            {\n              \"freq\": \"WEEKLY\",\n              \"wkst\": \"FR\",\n              \"opens_at\": \"10:30\",\n              \"closes_at\": \"13:30\"\n            }\n          ]\n        }\n      ],\n      \"phones\": [\n        {\n          \"number\": \"(301) 996-7803\",\n          \"type\": \"voice\",\n          \"languages\": [\n            {\n              \"name\": \"English\"\n            }\n          ]\n        }\n      ],\n      \"organization_identifiers\": [],\n      \"contacts\": [],\n      \"metadata\": [\n        {\n          \"resource_id\": \"beltsville-adventist-community-center\",\n          \"resource_type\": \"organization\",\n          \"last_action_date\": \"2024-01-01T00:00:00Z\",\n          \"last_action_type\": \"create\"\n        }\n      ],\n      \"attribute\": []\n    }\n  ],\n  \"service\": [\n    {\n      \"name\": \"Food Pantry\",\n      \"description\": \"Food distribution service\",\n      \"status\": \"active\",\n      \"phones\": [\n        {\n          \"number\": \"(301) 996-7803\",\n          \"type\": \"voice\",\n          \"languages\": [\n            {\n              \"name\": \"English\"\n            }\n          ]\n        }\n      ],\n      \"schedules\": [\n        {\n          \"freq\": \"WEEKLY\",\n          \"wkst\": \"TU\",\n          \"opens_at\": \"09:00\",\n          \"closes_at\": \"14:00\"\n        },\n        {\n          \"freq\": \"WEEKLY\",\n          \"wkst\": \"WE\",\n          \"opens_at\": \"09:00\",\n          \"closes_at\": \"14:00\"\n        },\n        {\n          \"freq\": \"WEEKLY\",\n          \"wkst\": \"FR\",\n          \"opens_at\": \"10:30\",\n          \"closes_at\": \"13:30\"\n        }\n      ]\n    }\n  ],\n  \"location\": [\n    {\n      \"name\": \"Beltsville Adventist Community Center\",\n      \"location_type\": \"physical\",\n      \"latitude\": 4729334.448006206,\n      \"longitude\": -8562848.184798952,\n      \"addresses\": [\n        {\n          \"address_1\": \"4200 Ammendale Rd.\",\n          \"city\": \"Beltsville\",\n          \"state_province\": \"MD\",\n          \"postal_code\": \"20705\",\n          \"country\": \"US\",\n          \"address_type\": \"physical\",\n          \"metadata\": [],\n          \"attribute\": []\n        }\n      ],\n      \"phones\": [\n        {\n          \"number\": \"(301) 996-7803\",\n          \"type\": \"voice\",\n          \"languages\": [\n            {\n              \"name\": \"English\"\n            }\n          ]\n        }\n      ],\n      \"accessibility\": [],\n      \"contacts\": [],\n      \"schedules\": [\n        {\n          \"freq\": \"WEEKLY\",\n          \"wkst\": \"TU\",\n          \"opens_at\": \"09:00\",\n          \"closes_at\": \"14:00\"\n        },\n        {\n          \"freq\": \"WEEKLY\",\n          \"wkst\": \"WE\",\n          \"opens_at\": \"09:00\",\n          \"closes_at\": \"14:00\"\n        },\n        {\n          \"freq\": \"WEEKLY\",\n          \"wkst\": \"FR\",\n          \"opens_at\": \"10:30\",\n          \"closes_at\": \"13:30\"\n        }\n      ],\n      \"languages\": [],\n      \"metadata\": []\n    }\n  ]\n}\n```",
  "job_id": "1754271748.026933",
  "timestamp": "2025-08-04T01:43:50.880562"
}