{
  "result": "{\n  \"organization\": {\n    \"id\": \"af97da40-6a11-4b50-8904-47a1220f8ed0\",\n    \"name\": \"Pilgrim Rest Church\",\n    \"alternate_name\": \"\",\n    \"description\": \"A church providing food pantry services.\",\n    \"locations\": [\n      {\n        \"id\": \"loc_1\",\n        \"name\": \"Pilgrim Rest Church\",\n        \"address\": {\n          \"address_1\": \"\",\n          \"address_2\": \"\",\n          \"city\": \"\",\n          \"state_province\": \"MS\",\n          \"postal_code\": \"\",\n          \"country\": \"US\"\n        },\n        \"location_type\": \"physical\",\n        \"coordinates\": {\n          \"latitude\": 33.4892841,\n          \"longitude\": -90.6506468\n        },\n        \"phones\": [],\n        \"emails\": [],\n        \"urls\": [],\n        \"services\": [\n          {\n            \"id\": \"svc_1\",\n            \"name\": \"Food Pantry\",\n            \"description\": \"Food pantry services offered by Pilgrim Rest Church.\",\n            \"status\": \"active\",\n            \"eligibility\": \"\",\n            \"fees\": \"\",\n            \"how_to_apply\": \"\",\n            \"schedule\": [],\n            \"offer_type\": \"\",\n            \"contact_details\": {\n              \"phones\": [],\n              \"emails\": [],\n              \"urls\": []\n            }\n          }\n        ],\n        \"metadata\": {\n          \"last_action_date\": \"2023-10-27\"\n        }\n      }\n    ],\n    \"metadata\": {\n      \"last_action_date\": \"2023-10-27\"\n    }\n  }\n}",
  "job_id": "1754630756.772375",
  "timestamp": "2025-08-08T06:16:53.820493"
}