{
  "content": "{\"name\": \"American Red Cross\", \"alternate_name\": \"\", \"description\": \"Food, Health Services \", \"email\": \"\", \"url\": \"www.redcross.org/local/new-jersey/about-us/locations/southern-nj.html\", \"status\": \"active\", \"address\": {\"address_1\": \"3 Parke Place Blvd\", \"address_2\": null, \"city\": \"Sewell\", \"state_province\": \"NJ\", \"postal_code\": \"08080\", \"country\": \"US\"}, \"location\": {\"latitude\": 39.7479974, \"longitude\": -75.1149246}, \"phones\": [{\"number\": \"(856) 256-8300\", \"type\": \"voice\"}]}",
  "metadata": {
    "scraper_id": "food_helpline_org",
    "source": "food_helpline_org"
  },
  "timestamp": "2025-08-08T05:09:38.596303"
}