{
  "content": "{\"name\": \"The Campaign Against Hunger\", \"address\": \"Phone: 718-773-3551 ext.151\", \"city\": \"\", \"state\": \"NY\", \"zip\": \"\", \"phone\": \"\", \"hours\": \"Monday: 09:30 AM - 06:30 PM Tuesday: 09:30 AM - 06:30 PM Wednesday: 09:30 AM - 06:30 PM Thursday: 09:30 AM - 06:30 PM Friday: 09:30 AM - 06:30 PM Saturday: Closed Sunday: Closed\", \"notes\": \"\", \"latitude\": 40.7130466, \"longitude\": -74.0072301, \"source\": \"food_bank_for_new_york_city_ny\", \"food_bank\": \"Food Bank For New York City\"}",
  "metadata": {
    "scraper_id": "food_bank_for_new_york_city_ny",
    "source": "food_bank_for_new_york_city_ny"
  },
  "timestamp": "2025-08-08T05:12:42.240158"
}