{
  "result": "{\n  \"organizations\": [\n    {\n      \"id\": \"org_1\",\n      \"name\": \"Helping Hands of Georgia Metro Inc.\",\n      \"alternate_name\": \"\",\n      \"description\": \"Provides food assistance services. Currently marked as no food distribution.\",\n      \"url\": \"https://gmhelpinghands.com/\",\n      \"email\": null,\n      \"status\": \"active\",\n      \"addresses\": [\n        {\n          \"id\": \"loc_1\",\n          \"address_type\": \"physical\",\n          \"address_1\": \"377 Valley Hill Road\",\n          \"address_2\": null,\n          \"city\": \"Riverdale\",\n          \"state_province\": \"GA\",\n          \"postal_code\": \"30274\",\n          \"country\": \"US\",\n          \"location_type\": \"physical\",\n          \"coordinates\": {\n            \"latitude\": 33.5706778,\n            \"longitude\": -84.4024515\n          }\n        }\n      ],\n      \"phones\": [\n        {\n          \"id\": \"phone_1\",\n          \"number\": \"404-301-8806\",\n          \"type\": \"voice\",\n          \"languages\": [\n            {\n              \"name\": \"English\"\n            }\n          ]\n        }\n      ],\n      \"services\": [\n        {\n          \"id\": \"svc_1\",\n          \"name\": \"Food Distribution\",\n          \"description\": \"No food distribution - marked unavailable\",\n          \"status\": \"active\",\n          \"locations\": [\n            \"loc_1\"\n          ],\n          \"regular_schedule\": [\n            {\n              \"id\": \"schedule_1\",\n              \"freq\": \"WEEKLY\",\n              \"wkst\": \"MO\",\n              \"days\": [\n                \"FR\"\n              ],\n              \"opens_at\": \"18:30\",\n              \"closes_at\": \"19:30\"\n            }\n          ]\n        }\n      ],\n      \"metadata\": {\n        \"last_action_date\": \"2023-10-27\"\n      }\n    }\n  ]\n}",
  "job_id": "1754629744.58774",
  "timestamp": "2025-08-08T05:30:43.967062"
}