{
  "content": "{\"id\": \"4a072a70-1d71-4f76-825d-aa45fdd53973\", \"name\": \"Reach Out Lodi\", \"alternate_name\": \"\", \"description\": \"\", \"email\": \"\", \"url\": \"\", \"status\": \"active\", \"address\": {\"address_1\": \"\", \"address_2\": \"\", \"city\": \"\", \"state_province\": \"\", \"postal_code\": \"\", \"country\": \"US\"}, \"phones\": [{\"number\": \"(608)5924592\", \"type\": \"voice\"}], \"location\": {\"latitude\": 43.3230972, \"longitude\": -89.5239181}, \"regular_schedule\": []}",
  "metadata": {
    "scraper_id": "getfull_app_api",
    "source": "getfull_app_api"
  },
  "timestamp": "2025-08-08T05:27:40.691806"
}