{
  "content": "{\"id\": \"48dae7f2-a3bc-4bfe-873a-4b53cc1ae7ec\", \"name\": \"First Presbyterian Church\", \"alternate_name\": \"\", \"description\": \"\", \"email\": \"\", \"url\": \"\", \"status\": \"active\", \"address\": {\"address_1\": \"\", \"address_2\": \"\", \"city\": \"\", \"state_province\": \"\", \"postal_code\": \"\", \"country\": \"US\"}, \"phones\": [{\"number\": \"(920)6852610\", \"type\": \"voice\"}], \"location\": {\"latitude\": 44.049549, \"longitude\": -88.74685699999999}, \"regular_schedule\": []}",
  "metadata": {
    "scraper_id": "getfull_app_api",
    "source": "getfull_app_api"
  },
  "timestamp": "2025-08-08T05:27:51.276633"
}