{
  "result": "{\n  \"organization\": {\n    \"id\": \"fad17f56-b77b-4c19-b27c-cb453d75acde\",\n    \"name\": \"Wesley United Methodist Church - Food Distribution Center\",\n    \"alternate_name\": null,\n    \"description\": \"Food distribution center operated by Wesley United Methodist Church.\",\n    \"email\": \"office@wesleyfresno.org\",\n    \"url\": null,\n    \"status\": \"active\",\n    \"address\": {\n      \"address_1\": null,\n      \"address_2\": null,\n      \"city\": null,\n      \"state_province\": \"CA\",\n      \"postal_code\": null,\n      \"country\": \"US\",\n      \"address_type\": \"physical\"\n    },\n    \"phones\": [\n      {\n        \"number\": \"559-224-1947\",\n        \"type\": \"voice\",\n        \"languages\": [\n          {\n            \"name\": \"English\"\n          }\n        ]\n      }\n    ],\n    \"metadata\": {\n      \"id\": \"org_fad17f56-b77b-4c19-b27c-cb453d75acde\",\n      \"last_action_date\": \"2023-10-27\"\n    }\n  },\n  \"locations\": [\n    {\n      \"id\": \"loc_fad17f56-b77b-4c19-b27c-cb453d75acde\",\n      \"name\": \"Wesley United Methodist Church - Food Distribution Center\",\n      \"alternate_name\": null,\n      \"description\": null,\n      \"status\": \"active\",\n      \"address\": {\n        \"address_1\": null,\n        \"address_2\": null,\n        \"city\": null,\n        \"state_province\": \"CA\",\n        \"postal_code\": null,\n        \"country\": \"US\",\n        \"address_type\": \"physical\"\n      },\n      \"phones\": [\n        {\n          \"number\": \"559-224-1947\",\n          \"type\": \"voice\",\n          \"languages\": [\n            {\n              \"name\": \"English\"\n            }\n          ]\n        }\n      ],\n      \"coordinates\": {\n        \"latitude\": 36.8153133,\n        \"longitude\": -119.7639556\n      },\n      \"location_type\": \"physical\",\n      \"metadata\": {\n        \"id\": \"loc_fad17f56-b77b-4c19-b27c-cb453d75acde\",\n        \"last_action_date\": \"2023-10-27\"\n      }\n    }\n  ],\n  \"services\": [\n    {\n      \"id\": \"svc_fad17f56-b77b-4c19-b27c-cb453d75acde\",\n      \"name\": \"Food Distribution\",\n      \"alternate_name\": null,\n      \"description\": \"Provides food distribution services.\",\n      \"status\": \"active\",\n      \"eligibility\": null,\n      \"fees\": null,\n      \"languages\": [\n        {\n          \"name\": \"English\"\n        }\n      ],\n      \"schedule\": [],\n      \"metadata\": {\n        \"id\": \"svc_fad17f56-b77b-4c19-b27c-cb453d75acde\",\n        \"last_action_date\": \"2023-10-27\"\n      }\n    }\n  ]\n}",
  "job_id": "1754630784.304345",
  "timestamp": "2025-08-08T06:29:21.098581"
}