{
  "content": "{\"name\": \"First United Methodist Church of Waycross\", \"alternate_name\": \"\", \"description\": \"https://www.facebook.com/waycrossfirst\", \"email\": \"\", \"url\": \"https://www.waycrossfirst.com/\", \"status\": \"active\", \"address\": {\"address_1\": \"410 Williams Street\", \"address_2\": null, \"city\": \"Waycross\", \"state_province\": \"GA\", \"postal_code\": \"31501\", \"country\": \"US\"}, \"location\": {\"latitude\": 31.20973579999999, \"longitude\": -82.355707}, \"phones\": [{\"number\": \"(229) 563-6357\", \"type\": \"voice\"}], \"regular_schedule\": [{\"weekday\": \"Thursday\", \"opens_at\": \"13:00\", \"closes_at\": \"20:00\"}]}",
  "metadata": {
    "scraper_id": "food_helpline_org",
    "source": "food_helpline_org"
  },
  "timestamp": "2025-08-06T08:40:34.570269"
}