{
  "result": "{\n  \"version\": \"3.1.1\",\n  \"organizations\": [\n    {\n      \"id\": \"org_10081\",\n      \"name\": \"Hispanic SDA-Olathe\",\n      \"description\": \"Hispanic SDA-Olathe provides food pantry services, including the TEFAP Program.\",\n      \"addresses\": [\n        {\n          \"address_type\": \"physical\",\n          \"street1\": \"203 N 4th St\",\n          \"street2\": null,\n          \"city\": \"Olathe\",\n          \"state_province\": \"CO\",\n          \"postal_code\": \"81425\",\n          \"country\": \"US\",\n          \"coordinates\": {\n            \"latitude\": 38.6121599,\n            \"longitude\": -107.9821846\n          }\n        }\n      ],\n      \"phones\": [\n        {\n          \"number\": \"970-201-7219\",\n          \"type\": \"voice\",\n          \"languages\": [\n            {\n              \"name\": \"English\"\n            }\n          ]\n        }\n      ],\n      \"metadata\": {\n        \"last_action_date\": \"2023-10-27\",\n        \"source_id\": \"10081\"\n      }\n    }\n  ],\n  \"locations\": [\n    {\n      \"id\": \"loc_12860\",\n      \"organization_id\": \"org_10081\",\n      \"name\": \"Hispanic SDA-Olathe\",\n      \"location_type\": \"physical\",\n      \"addresses\": [\n        {\n          \"address_type\": \"physical\",\n          \"street1\": \"203 N 4th St\",\n          \"street2\": null,\n          \"city\": \"Olathe\",\n          \"state_province\": \"CO\",\n          \"postal_code\": \"81425\",\n          \"country\": \"US\",\n          \"coordinates\": {\n            \"latitude\": 38.6121599,\n            \"longitude\": -107.9821846\n          }\n        }\n      ],\n      \"phones\": [\n        {\n          \"number\": \"970-201-7219\",\n          \"type\": \"voice\",\n          \"languages\": [\n            {\n              \"name\": \"English\"\n            }\n          ]\n        }\n      ],\n      \"metadata\": {\n        \"last_action_date\": \"2023-10-27\",\n        \"source_id\": \"12860\"\n      }\n    }\n  ],\n  \"services\": [\n    {\n      \"id\": \"svc_1\",\n      \"organization_id\": \"org_10081\",\n      \"location_id\": \"loc_12860\",\n      \"name\": \"Food Pantry\",\n      \"description\": \"Provides food pantry services, including the TEFAP Program.\",\n      \"status\": \"active\",\n      \"service_areas\": [],\n      \"languages\": [],\n      \"schedule\": {\n        \"freq\": null,\n        \"interval\": null,\n        \"skip\": null,\n        \"wkst\": \"MO\",\n        \"days\": [],\n        \"start_time\": null,\n        \"end_time\": null\n      },\n      \"metadata\": {\n        \"last_action_date\": \"2023-10-27\",\n        \"source_id\": \"10081\"\n      }\n    }\n  ],\n  \"metadata\": {\n    \"last_action_date\": \"2023-10-27\"\n  }\n}",
  "job_id": "1754631596.558418",
  "timestamp": "2025-08-08T07:26:35.426564"
}