{
  "content": "{\"id\": \"3054d226-2252-4299-abe4-651eb21e96b2\", \"name\": \"Manna Ministry - Food Distribution Center\", \"alternate_name\": \"\", \"description\": \"\", \"email\": \"dixie@mannaministry.net\", \"url\": \"\", \"status\": \"active\", \"address\": {\"address_1\": \"\", \"address_2\": \"\", \"city\": \"\", \"state_province\": \"\", \"postal_code\": \"\", \"country\": \"US\"}, \"phones\": [{\"number\": \"(601)7992121\", \"type\": \"voice\"}], \"location\": {\"latitude\": 30.5100979, \"longitude\": -89.6871089}, \"regular_schedule\": []}",
  "metadata": {
    "scraper_id": "getfull_app_api",
    "source": "getfull_app_api"
  },
  "timestamp": "2025-08-08T05:25:39.631721"
}