{
  "result": "{\n  \"organization\": {\n    \"id\": \"org_1\",\n    \"name\": \"First United Methodist Church\",\n    \"description\": \"A United Methodist Church providing community services.\",\n    \"alternate_names\": [],\n    \"urls\": [],\n    \"emails\": [],\n    \"logos\": [],\n    \"addresses\": [\n      {\n        \"id\": \"loc_1\",\n        \"address_type\": \"physical\",\n        \"address_lines\": [],\n        \"city\": null,\n        \"state_province\": null,\n        \"postal_code\": null,\n        \"country\": \"US\",\n        \"coordinates\": {\n          \"latitude\": 34.0263801,\n          \"longitude\": -117.9507701\n        },\n        \"location_type\": \"physical\"\n      }\n    ],\n    \"phones\": [\n      {\n        \"id\": \"phone_1\",\n        \"number\": \"6263361927\",\n        \"extension\": null,\n        \"type\": \"voice\",\n        \"languages\": [\n          {\n            \"name\": \"English\"\n          }\n        ]\n      }\n    ]\n  },\n  \"services\": [\n    {\n      \"id\": \"svc_1\",\n      \"organization_id\": \"org_1\",\n      \"name\": \"First United Methodist Church Services\",\n      \"description\": \"General services offered by First United Methodist Church.\",\n      \"status\": \"active\",\n      \"locations\": [\n        {\n          \"id\": \"loc_1\"\n        }\n      ],\n      \"schedule\": {\n        \"id\": \"schedule_1\",\n        \"description\": null,\n        \"freq\": null,\n        \"freq_type\": null,\n        \"interval\": null,\n        \"days_of_week\": [],\n        \"skipped_weeks\": [],\n        \"start_date\": null,\n        \"end_date\": null,\n        \"times\": [],\n        \"wkst\": \"MO\",\n        \"closed\": []\n      },\n      \"eligibility\": null,\n      \"fees\": null,\n      \"application_process\": null,\n      \"notes\": null,\n      \"urls\": [],\n      \"emails\": [],\n      \"phones\": []\n    }\n  ],\n  \"metadata\": {\n    \"last_action_date\": \"2023-10-27\",\n    \"source\": \"manual\"\n  }\n}",
  "job_id": "1754630759.690668",
  "timestamp": "2025-08-08T06:18:20.978945"
}