{
  "result": "{\n  \"type\": \"Organization\",\n  \"hs_version\": \"3.1.1\",\n  \"organization\": {\n    \"id\": \"org_1\",\n    \"name\": \"Avonmore First Presbyterian Church\",\n    \"description\": \"Avonmore First Presbyterian Church offers a Hot/Cold Meal Program.\",\n    \"addresses\": [\n      {\n        \"address_type\": \"physical\",\n        \"street\": \"518 Indiana Ave\",\n        \"city\": \"Avonmore\",\n        \"state_province\": \"PA\",\n        \"postal_code\": \"15618\",\n        \"country\": \"US\",\n        \"coordinates\": {\n          \"latitude\": 40.5294159,\n          \"longitude\": -79.4642065\n        }\n      }\n    ],\n    \"phones\": [],\n    \"email\": [],\n    \"urls\": [],\n    \"metadata\": {\n      \"last_action_date\": \"2023-10-27\"\n    }\n  },\n  \"locations\": [\n    {\n      \"id\": \"loc_1\",\n      \"name\": \"Avonmore First Presbyterian Church\",\n      \"location_type\": \"physical\",\n      \"addresses\": [\n        {\n          \"address_type\": \"physical\",\n          \"street\": \"518 Indiana Ave\",\n          \"city\": \"Avonmore\",\n          \"state_province\": \"PA\",\n          \"postal_code\": \"15618\",\n          \"country\": \"US\",\n          \"coordinates\": {\n            \"latitude\": 40.5294159,\n            \"longitude\": -79.4642065\n          }\n        }\n      ],\n      \"phones\": [],\n      \"email\": [],\n      \"urls\": [],\n      \"metadata\": {\n        \"last_action_date\": \"2023-10-27\"\n      }\n    }\n  ],\n  \"services\": [\n    {\n      \"id\": \"svc_1\",\n      \"name\": \"Hot/Cold Meal Program\",\n      \"description\": \"Provides a hot or cold meal.\",\n      \"organization_id\": \"org_1\",\n      \"location_ids\": [\n        \"loc_1\"\n      ],\n      \"status\": \"active\",\n      \"eligibility\": [],\n      \"fees\": [],\n      \"schedule\": [\n        {\n          \"freq\": \"WEEKLY\",\n          \"wkst\": \"MO\",\n          \"days\": [\n            \"MO\",\n            \"WE\"\n          ],\n          \"times\": [\n            {\n              \"open_time\": \"11:00\",\n              \"close_time\": \"12:00\"\n            },\n            {\n              \"open_time\": \"11:00\",\n              \"close_time\": \"12:00\"\n            }\n          ]\n        }\n      ],\n      \"metadata\": {\n        \"last_action_date\": \"2023-10-27\"\n      }\n    }\n  ]\n}",
  "job_id": "1754631603.708566",
  "timestamp": "2025-08-08T07:29:31.887433"
}