{
  "result": "{\n  \"organizations\": [\n    {\n      \"id\": \"org_1\",\n      \"name\": \"New Life Cathedral - Food Distribution Center\",\n      \"alternate_name\": null,\n      \"description\": \"New Life Cathedral operates a food distribution center.\",\n      \"email\": \"newlifechurchowb@gmail.com\",\n      \"url\": null,\n      \"status\": \"active\",\n      \"addresses\": [\n        {\n          \"id\": \"loc_1\",\n          \"address_type\": \"physical\",\n          \"address_1\": null,\n          \"address_2\": null,\n          \"city\": null,\n          \"state_province\": \"MO\",\n          \"postal_code\": null,\n          \"country\": \"US\",\n          \"coordinates\": {\n            \"latitude\": 39.7688345,\n            \"longitude\": -94.8503173\n          },\n          \"location_type\": \"physical\"\n        }\n      ],\n      \"phones\": [],\n      \"services\": [\n        {\n          \"id\": \"svc_1\",\n          \"name\": \"Food Distribution\",\n          \"description\": \"Provides food distribution services.\",\n          \"status\": \"active\",\n          \"locations\": [\n            \"loc_1\"\n          ],\n          \"schedule\": [],\n          \"metadata\": {\n            \"last_action_date\": \"2023-10-27\"\n          }\n        }\n      ],\n      \"metadata\": {\n        \"last_action_date\": \"2023-10-27\"\n      }\n    }\n  ]\n}",
  "job_id": "1754630831.256805",
  "timestamp": "2025-08-08T06:49:25.536593"
}