{
  "content": "{\"name\": \"Goodwill Tenants Association Inc.\", \"alternate_name\": \"\", \"description\": null, \"email\": \"\", \"url\": \"https://www.facebook.com/GoodwillNyNj\", \"status\": \"active\", \"address\": {\"address_1\": \"4-21 27th Ave\", \"address_2\": null, \"city\": \"New York\", \"state_province\": \"NY\", \"postal_code\": \"11102\", \"country\": \"US\"}, \"location\": {\"latitude\": 40.7743181, \"longitude\": -73.9311433}, \"phones\": [{\"number\": \"(718) 932-4200\", \"type\": \"voice\"}], \"regular_schedule\": [{\"weekday\": \"Friday\", \"opens_at\": \"19:00\", \"closes_at\": \"21:00\"}]}",
  "metadata": {
    "scraper_id": "food_helpline_org",
    "source": "food_helpline_org"
  },
  "timestamp": "2025-08-06T08:41:22.737286"
}