{
  "content": "{\"locationId\": \"10814\", \"organizationId\": \"8451\", \"name\": \"Mescalero Apache Tribe\", \"address1\": \"108 Central Avenue\", \"address2\": \"\", \"city\": \"Mescalero\", \"state\": \"NM\", \"zipCode\": \"88340\", \"country\": null, \"phone\": \"575-937-8006\", \"phoneExt\": \"\", \"website\": null, \"latitude\": \"33.1575854\", \"longitude\": \"-105.7741541\", \"foodPrograms\": \"Pop-Up/Mobile Resource\", \"serviceAreas\": \"\", \"languages\": \"\", \"features\": \"\", \"aboutUs\": \"\", \"notes\": \"\", \"contactName\": \"\", \"contactPhone\": \"\", \"contactEmail\": \"\", \"servicePrograms\": \"\", \"foodServiceTypes\": \"\", \"dietRestrictions\": \"\", \"foodOfferings\": \"\", \"networkAffiliations\": [{\"regionId\": 71, \"regionName\": \"Roadrunner Food Bank of New Mexico\", \"logoBlobNameSmall\": \"d2c42119-4ccf-487d-89a3-a39cf3f3228b.png\", \"website\": \"https://www.rrfb.org/\"}], \"timeZoneName\": \"Mountain Standard Time\", \"timeZoneCode\": \"MT\", \"offsetHours\": \"-6\", \"schedules\": [\"Thursday 12:20 PM-1:20 PM (Open until all food is distributed)\"], \"services\": [], \"specialHours\": []}",
  "metadata": {
    "scraper_id": "vivery_api",
    "source": "vivery_api"
  },
  "timestamp": "2025-08-06T08:46:40.156387"
}