{
  "content": "{\"locationId\": \"1172\", \"organizationId\": \"1025\", \"name\": \"St. Anastasia Soup Kitchen\", \"address1\": \"624 Douglas Avenue\", \"address2\": \"\", \"city\": \"Waukegan\", \"state\": \"IL\", \"zipCode\": \"60085\", \"country\": null, \"phone\": \"847-623-2875\", \"phoneExt\": \"255\", \"website\": \"\", \"latitude\": \"42.3767291\", \"longitude\": \"-87.838974\", \"foodPrograms\": \"Hot/Cold Meal Program\", \"serviceAreas\": \"\", \"languages\": \"\", \"features\": \"\", \"aboutUs\": \"\", \"notes\": \"\", \"contactName\": \"\", \"contactPhone\": \"847-623-2875\", \"contactEmail\": \"\", \"servicePrograms\": \"\", \"foodServiceTypes\": \"\", \"dietRestrictions\": \"\", \"foodOfferings\": \"\", \"networkAffiliations\": [{\"regionId\": 2, \"regionName\": \"Northern Illinois Food Bank\", \"logoBlobNameSmall\": \"dbf64577-4f05-4753-a6ec-ebbbd9c99e9c.png\", \"website\": \"solvehungertoday.org\"}], \"timeZoneName\": \"Central Standard Time\", \"timeZoneCode\": \"CT\", \"offsetHours\": \"-5\", \"schedules\": [\"Monday 5:30 PM-6:30 PM\"], \"services\": [], \"specialHours\": []}",
  "metadata": {
    "scraper_id": "vivery_api",
    "source": "vivery_api"
  },
  "timestamp": "2025-08-08T05:40:08.106027"
}